nextsms/__init__.py
nextsms-0.4.dist-info/LICENSE
nextsms-0.4.dist-info/METADATA
nextsms-0.4.dist-info/WHEEL
nextsms-0.4.dist-info/top_level.txt
nextsms-0.4.dist-info/RECORD
