Metadata-Version: 2.1
Name: nextsms
Version: 0.4
Summary: Python package to easy integration with NextSms API for bulksms
Home-page: https://github.com/Kalebu/nextsms
Author: Jordan Kalebu
Author-email: isaackeinstein@gmail.com
License: MIT
Download-URL: https://github.com/Kalebu/nextsms/archive/0.2.tar.gz
Keywords: nextsms,python-nextsms,tanzania sms,nextsms-tanzania
Platform: UNKNOWN
Classifier: Development Status :: 3 - Alpha
Classifier: Intended Audience :: Developers
Classifier: Topic :: Software Development :: Build Tools
Classifier: License :: OSI Approved :: MIT License
Classifier: Programming Language :: Python :: 3.6
Classifier: Programming Language :: Python :: 3.7
Classifier: Programming Language :: Python :: 3.8
Classifier: Programming Language :: Python :: 3.9
Requires-Python: >=3.6
Requires-Dist: requests
